README.rst
setup.py
geoql/__init__.py
geoql/geoql.py
geoql.egg-info/PKG-INFO
geoql.egg-info/SOURCES.txt
geoql.egg-info/dependency_links.txt
geoql.egg-info/requires.txt
geoql.egg-info/top_level.txt