Metadata-Version: 1.0
Name: geoql
Version: 0.0.8.0
Summary: Library for performing queries and transformations on GeoJSON data (with emphasis on support for abstract graph representations).
Home-page: https://github.com/Data-Mechanics/geoql
Author: Andrei Lapets
Author-email: a@lapets.io
License: MIT
Platform: UNKNOWN
